nets/__init__.py
nets/mobilenet.py
nets/resnet50.py
nets/vgg16.py
utils/__init__.py
utils/callbacks.py
utils/dataloader.py
utils/utils.py
utils/utils_fit.py
chushai-0.0.6.dist-info/METADATA
chushai-0.0.6.dist-info/WHEEL
chushai-0.0.6.dist-info/top_level.txt
chushai-0.0.6.dist-info/RECORD
