Metadata-Version: 2.1
Name: chushai
Version: 0.0.6
Summary: chushai use
Author: WangMengtian
Author-email: 19845175463@163.com
License: apache 3.0
Platform: UNKNOWN
